rnapykin-0.3.0.dist-info/METADATA
rnapykin-0.3.0.dist-info/WHEEL
rnapykin-0.3.0.dist-info/license_files/LICENSE
rnapykin.libs/libfontconfig-ebabad56.so.1
rnapykin.libs/libuuid-fea9df74.so.1
rnapykin.libs/libfreetype-0f217dc2.so.6
rnapykin.libs/libpng16-4a697b98.so.16
rnapykin/__init__.py
rnapykin/rnapykin.cpython-38-x86_64-linux-gnu.so
rnapykin-0.3.0.dist-info/RECORD
